odoo8_addon_l10n_fr_naf_ape-8.0.1.0.0.99.dev16-py2.7-nspkg.pth
odoo8_addon_l10n_fr_naf_ape-8.0.1.0.0.99.dev16.dist-info/METADATA
odoo8_addon_l10n_fr_naf_ape-8.0.1.0.0.99.dev16.dist-info/RECORD
odoo8_addon_l10n_fr_naf_ape-8.0.1.0.0.99.dev16.dist-info/WHEEL
odoo8_addon_l10n_fr_naf_ape-8.0.1.0.0.99.dev16.dist-info/namespace_packages.txt
odoo8_addon_l10n_fr_naf_ape-8.0.1.0.0.99.dev16.dist-info/top_level.txt
odoo_addons/l10n_fr_naf_ape/README.rst
odoo_addons/l10n_fr_naf_ape/__init__.py
odoo_addons/l10n_fr_naf_ape/__openerp__.py
odoo_addons/l10n_fr_naf_ape/partner.py
odoo_addons/l10n_fr_naf_ape/partner_view.xml
odoo_addons/l10n_fr_naf_ape/data/res.partner.category.csv
odoo_addons/l10n_fr_naf_ape/i18n/am.po
odoo_addons/l10n_fr_naf_ape/i18n/ar.po
odoo_addons/l10n_fr_naf_ape/i18n/bg.po
odoo_addons/l10n_fr_naf_ape/i18n/bs.po
odoo_addons/l10n_fr_naf_ape/i18n/ca.po
odoo_addons/l10n_fr_naf_ape/i18n/cs.po
odoo_addons/l10n_fr_naf_ape/i18n/da.po
odoo_addons/l10n_fr_naf_ape/i18n/de.po
odoo_addons/l10n_fr_naf_ape/i18n/el_GR.po
odoo_addons/l10n_fr_naf_ape/i18n/en_GB.po
odoo_addons/l10n_fr_naf_ape/i18n/es.po
odoo_addons/l10n_fr_naf_ape/i18n/es_CR.po
odoo_addons/l10n_fr_naf_ape/i18n/es_EC.po
odoo_addons/l10n_fr_naf_ape/i18n/es_MX.po
odoo_addons/l10n_fr_naf_ape/i18n/es_VE.po
odoo_addons/l10n_fr_naf_ape/i18n/et.po
odoo_addons/l10n_fr_naf_ape/i18n/eu.po
odoo_addons/l10n_fr_naf_ape/i18n/fi.po
odoo_addons/l10n_fr_naf_ape/i18n/fr.po
odoo_addons/l10n_fr_naf_ape/i18n/fr_CA.po
odoo_addons/l10n_fr_naf_ape/i18n/fr_CH.po
odoo_addons/l10n_fr_naf_ape/i18n/gl.po
odoo_addons/l10n_fr_naf_ape/i18n/hr.po
odoo_addons/l10n_fr_naf_ape/i18n/hr_HR.po
odoo_addons/l10n_fr_naf_ape/i18n/hu.po
odoo_addons/l10n_fr_naf_ape/i18n/id.po
odoo_addons/l10n_fr_naf_ape/i18n/it.po
odoo_addons/l10n_fr_naf_ape/i18n/ja.po
odoo_addons/l10n_fr_naf_ape/i18n/l10n_fr_naf_ape.pot
odoo_addons/l10n_fr_naf_ape/i18n/lt.po
odoo_addons/l10n_fr_naf_ape/i18n/lv.po
odoo_addons/l10n_fr_naf_ape/i18n/mk.po
odoo_addons/l10n_fr_naf_ape/i18n/mn.po
odoo_addons/l10n_fr_naf_ape/i18n/nb.po
odoo_addons/l10n_fr_naf_ape/i18n/nb_NO.po
odoo_addons/l10n_fr_naf_ape/i18n/nl.po
odoo_addons/l10n_fr_naf_ape/i18n/nl_BE.po
odoo_addons/l10n_fr_naf_ape/i18n/pl.po
odoo_addons/l10n_fr_naf_ape/i18n/pt.po
odoo_addons/l10n_fr_naf_ape/i18n/pt_BR.po
